basilisp_kernel/__init__.py
basilisp_kernel/__main__.py
basilisp_kernel/kernel.py
basilisp_kernel/nrepl_server.lpy
basilisp_kernel-1.3.0.data/data/share/jupyter/kernels/basilisp/kernel.json
basilisp_kernel-1.3.0.dist-info/METADATA
basilisp_kernel-1.3.0.dist-info/WHEEL
basilisp_kernel-1.3.0.dist-info/licenses/LICENSE
basilisp_kernel-1.3.0.dist-info/RECORD
