Metadata-Version: 2.4
Name: basilisp-kernel
Version: 1.3.0
Summary: Basilisp kernel for Jupyter
Project-URL: Homepage, https://github.com/ikappaki/basilisp-kernel
Author: ikappaki
License: BSD 3-Clause License
License-File: LICENSE
Classifier: License :: OSI Approved :: BSD License
Classifier: Programming Language :: Python :: 3
Requires-Python: >=3.9
Requires-Dist: basilisp-nrepl-async>=0.1.0
Requires-Dist: basilisp>=0.4.0
Requires-Dist: ipykernel
Requires-Dist: jupyter-client
Provides-Extra: test
Requires-Dist: jupyter-kernel-test; extra == 'test'
